email_views/__init__.py
email_views/emails.py
tests/__init__.py
tests/settings.py
tests/test_core.py
djangoemailviews-0.0.1.dist-info/METADATA
djangoemailviews-0.0.1.dist-info/WHEEL
djangoemailviews-0.0.1.dist-info/top_level.txt
djangoemailviews-0.0.1.dist-info/RECORD
