Metadata-Version: 2.1
Name: djangoemailviews
Version: 0.0.1
Summary: Usage Django views ideology for emails
Home-page: UNKNOWN
Author: Anatoly Gusev
Author-email: gt@zerolab.tech
License: UNKNOWN
Platform: UNKNOWN
Classifier: Programming Language :: Python :: 3
Classifier: License :: OSI Approved :: MIT License
Classifier: Operating System :: OS Independent
